Metadata-Version: 2.1
Name: vasyapauk228nagibator
Version: 0.0.1
Summary: My Package
Author: Eduard
Author-email: bel.gpt@gmail.com
